preferences/__init__.py
preferences/admin.py
preferences/context_processors.py
preferences/managers.py
preferences/models.py
preferences/migrations/0001_initial.py
preferences/migrations/__init__.py
django3_preferences-0.0.1.dist-info/LICENSE
django3_preferences-0.0.1.dist-info/METADATA
django3_preferences-0.0.1.dist-info/WHEEL
django3_preferences-0.0.1.dist-info/top_level.txt
django3_preferences-0.0.1.dist-info/RECORD
