Metadata-Version: 2.1
Name: django3-preferences
Version: 0.0.1
Summary: Adds simple preferences to the admin panel on Django 3.1 and above
Home-page: https://github.com/lechien73/django3-preferences
Author: Matt Rudge
Author-email: mattrudgesoftware@gmail.com
License: MIT
Platform: UNKNOWN
Classifier: Programming Language :: Python
Classifier: Programming Language :: Python :: 3
Classifier: Programming Language :: Python :: 3.4
Classifier: Programming Language :: Python :: 3.5
Classifier: Programming Language :: Python :: 3.6
Classifier: Programming Language :: Python :: 3.7
Classifier: Framework :: Django :: 3.1
Classifier: Framework :: Django :: 3.2
Classifier: License :: OSI Approved :: BSD License
Classifier: Development Status :: 5 - Production/Stable
Classifier: Operating System :: OS Independent
Classifier: Framework :: Django
Classifier: Intended Audience :: Developers
Classifier: Topic :: Internet :: WWW/HTTP :: Dynamic Content
License-File: LICENSE
Requires-Dist: django
